agent_control_layer/__init__.py
agent_control_layer/config.py
agent_control_layer/langgraph/__init__.py
agent_control_layer/langgraph/tools.py
agent_control_layer/layer.py
agent_control_layer-0.1.1.dist-info/WHEEL
agent_control_layer-0.1.1.dist-info/METADATA
agent_control_layer-0.1.1.dist-info/RECORD
