Metadata-Version: 2.3
Name: agent-control-layer
Version: 0.1.1
Summary: Datagusto Agent Control Layer
Requires-Dist: langchain-core>=0.3.67
Requires-Dist: langgraph>=0.5.1
Requires-Dist: pydantic>=2.0.0
Requires-Dist: pyyaml>=6.0.2
Requires-Python: >=3.9
